<!DOCTYPE ui:UiBinder SYSTEM "http://dl.google.com/gwt/DTD/xhtml.ent">
<ui:UiBinder xmlns:ui="urn:ui:com.google.gwt.uibinder" xmlns:g="urn:import:com.google.gwt.user.client.ui" 
    xmlns:sg="urn:import:org.ednovo.gooru.client.mvp.home"
    xmlns:panel="urn:import:org.ednovo.gooru.client.ui"
    xmlns:uc="urn:import:org.ednovo.gooru.client.uc">
	<ui:style src=""></ui:style>
	<g:HTMLPanel>
	<g:HTMLPanel ui:field="startContainer">
		<g:HTMLPanel styleName="standardBlueBand">
			<g:HTMLPanel styleName="container" ui:field="mainContainer">
				<g:HTMLPanel styleName="no-gutter">
					<g:HTMLPanel styleName="col-md-5 col-sm-5">
					<uc:H2Panel ui:field="titlePanel"></uc:H2Panel>
					</g:HTMLPanel>
					<g:HTMLPanel styleName="col-md-7 col-sm-7 topBlueRight">
						 <g:HTMLPanel styleName="settingsMenu">
						<!--   <g:Button styleName="primary" ui:field="studentPreviewbtn"></g:Button> -->
						 <panel:HTMLEventPanel styleName="classAnrSettings" ui:field="studentAnr"><img src="images/Classpage/studentsIco.png"/><g:InlineLabel ui:field="studentLbl"/></panel:HTMLEventPanel>
						 <panel:HTMLEventPanel styleName="classAnrSettings" ui:field="dashBoardAnr"><img src="images/Classpage/dashbardIcon.png"/><g:InlineLabel ui:field="dashBoardLbl"/></panel:HTMLEventPanel>
						 <panel:HTMLEventPanel styleName="classAnrSettings" ui:field="classSettingsAnr"><img src="images/Classpage/classSettingsIco.png"/><g:InlineLabel ui:field="settingsLbl"/></panel:HTMLEventPanel>
						 </g:HTMLPanel>
						<g:HTMLPanel styleName="rightWhiteBox"><uc:SpanPanel ui:field="classCodePanel"></uc:SpanPanel></g:HTMLPanel>
					</g:HTMLPanel>
				    <g:HTMLPanel styleName="clearfix"></g:HTMLPanel>
				</g:HTMLPanel>
			</g:HTMLPanel>
		</g:HTMLPanel>
		<g:HTMLPanel styleName="mainBodySupportBlock">
			<g:HTMLPanel styleName="container">
				<g:HTMLPanel styleName="row">
					<!-- <g:HTMLPanel styleName="whiteBG" ui:field="tabTitleContainer">
						<g:HTMLPanel styleName="MainHeader">
						<uc:H3Panel ui:field="tabTitle"></uc:H3Panel>
						</g:HTMLPanel>
					</g:HTMLPanel> -->
					<g:SimplePanel ui:field="bodyMenuView"></g:SimplePanel>
					<g:FlowPanel ui:field="reportBox"></g:FlowPanel>
				</g:HTMLPanel>
			</g:HTMLPanel>
		</g:HTMLPanel>
	</g:HTMLPanel>
	<!-- <sg:FooterUc /> -->
  </g:HTMLPanel>
</ui:UiBinder> 


